sraverify/__init__.py
sraverify/main.py
sraverify/checks/__init__.py
sraverify/checks/accessanalyzer/SRA_IAA_1.py
sraverify/checks/accessanalyzer/SRA_IAA_2.py
sraverify/checks/accessanalyzer/SRA_IAA_3.py
sraverify/checks/accessanalyzer/SRA_IAA_4.py
sraverify/checks/accessanalyzer/__init__.py
sraverify/checks/cloudtrail/SRA-CT-1.py
sraverify/checks/cloudtrail/SRA-CT-10.py
sraverify/checks/cloudtrail/SRA-CT-11.py
sraverify/checks/cloudtrail/SRA-CT-12.py
sraverify/checks/cloudtrail/SRA-CT-13.py
sraverify/checks/cloudtrail/SRA-CT-2.py
sraverify/checks/cloudtrail/SRA-CT-3.py
sraverify/checks/cloudtrail/SRA-CT-4.py
sraverify/checks/cloudtrail/SRA-CT-5.py
sraverify/checks/cloudtrail/SRA-CT-6.py
sraverify/checks/cloudtrail/SRA-CT-7.py
sraverify/checks/cloudtrail/SRA-CT-8.py
sraverify/checks/cloudtrail/SRA-CT-9.py
sraverify/checks/cloudtrail/__init__.py
sraverify/checks/config/SRA-CONFIG-1.py
sraverify/checks/config/__init__.py
sraverify/core/__init__.py
sraverify/core/check.py
sraverify/core/logging.py
sraverify/core/session.py
sraverify/lib/__init__.py
sraverify/lib/audit_info.py
sraverify/lib/banner.py
sraverify/lib/check_loader.py
sraverify/lib/org_mgmt_checker.py
sraverify/lib/outputs.py
sraverify/lib/progress.py
sraverify/lib/regions.py
sraverify/lib/session.py
sraverify/services/__init__.py
sraverify/services/accessanalyzer/__init__.py
sraverify/services/accessanalyzer/base.py
sraverify/services/accessanalyzer/client.py
sraverify/services/accessanalyzer/checks/__init__.py
sraverify/services/accessanalyzer/checks/sra_accessanalyzer_01.py
sraverify/services/accessanalyzer/checks/sra_accessanalyzer_02.py
sraverify/services/accessanalyzer/checks/sra_accessanalyzer_03.py
sraverify/services/accessanalyzer/checks/sra_accessanalyzer_04.py
sraverify/services/account/__init__.py
sraverify/services/account/base.py
sraverify/services/account/client.py
sraverify/services/account/checks/__init__.py
sraverify/services/account/checks/sra_account_01.py
sraverify-0.1.1.dist-info/LICENSE
sraverify-0.1.1.dist-info/METADATA
sraverify-0.1.1.dist-info/NOTICE
sraverify-0.1.1.dist-info/WHEEL
sraverify-0.1.1.dist-info/entry_points.txt
sraverify-0.1.1.dist-info/top_level.txt
sraverify-0.1.1.dist-info/RECORD
