Metadata-Version: 2.1
Name: sraverify
Version: 0.1.1
Summary: AWS Security Reference Architecture Verification Tool
Home-page: https://github.com/awslabs/sra-verify
Author: SRA Verify team
Author-email: schiefj@amazon.com
Classifier: Programming Language :: Python :: 3
Classifier: License :: OSI Approved :: Apache Software License
Classifier: Operating System :: OS Independent
Requires-Python: >=3.8
License-File: LICENSE
License-File: NOTICE
Requires-Dist: boto3>=1.26.0
Requires-Dist: colorama>=0.4.4
